<annotation>
    <folder>train</folder>
    <filename>IIa_BA0710.png</filename>
    <size>
        <width>2480</width>
        <height>3508</height>
        <depth>3</depth>
    </size>
    <object>
        <name>window</name>
        <pose>Unspecified</pose>
        <truncated>0</truncated>
        <occluded>0</occluded>
        <difficult>0</difficult>
        <polygon>
            <x1>2189.726140</x1>
            <y1>1165.603976</y1>
            <x2>2223.331363</x2>
            <y2>1167.468005</y2>
            <x3>2221.607236</x3>
            <y3>1240.945864</y3>
            <x4>2190.026209</x4>
            <y4>1241.764715</y4>
            <x5>2190.303392</x5>
            <y5>1170.809526</y5>
        </polygon>
        <bndbox>
            <xmin>2189.726074</xmin>
            <ymin>1165.604004</ymin>
            <xmax>2223.331299</xmax>
            <ymax>1241.764771</ymax>
        </bndbox>
    </object>
    <object>
        <name>window</name>
        <pose>Unspecified</pose>
        <truncated>0</truncated>
        <occluded>0</occluded>
        <difficult>0</difficult>
        <polygon>
            <x1>2189.344696</x1>
            <y1>1003.308795</y1>
            <x2>2222.949919</x2>
            <y2>1005.172824</y2>
            <x3>2221.225792</x3>
            <y3>1078.650683</y3>
            <x4>2189.644765</x4>
            <y4>1079.469534</y4>
            <x5>2189.921948</x5>
            <y5>1008.514345</y5>
        </polygon>
        <bndbox>
            <xmin>2189.344727</xmin>
            <ymin>1003.308777</ymin>
            <xmax>2222.949951</xmax>
            <ymax>1079.469482</ymax>
        </bndbox>
    </object>
    <object>
        <name>door</name>
        <pose>Unspecified</pose>
        <truncated>0</truncated>
        <occluded>0</occluded>
        <difficult>0</difficult>
        <polygon>
            <x1>1579.311569</x1>
            <y1>1442.547936</y1>
            <x2>1583.488485</x2>
            <y2>1449.313889</y2>
            <x3>1595.064744</x3>
            <y3>1487.281578</y3>
            <x4>1603.981482</x4>
            <y4>1505.220740</y4>
            <x5>1636.189425</x5>
            <y5>1532.806894</y5>
            <x6>1666.072327</x6>
            <y6>1540.462460</y6>
            <x7>1677.615953</x7>
            <y7>1539.368807</y7>
            <x8>1681.336020</x8>
            <y8>1535.426762</y8>
            <x9>1678.978346</x9>
            <y9>1452.390807</y9>
            <x10>1687.707449</x10>
            <y10>1451.305316</y10>
            <x11>1687.707449</x11>
            <y11>1436.957251</y11>
            <x12>1578.699716</x12>
            <y12>1431.660383</y12>
        </polygon>
        <bndbox>
            <xmin>1578.699707</xmin>
            <ymin>1431.660400</ymin>
            <xmax>1687.707397</xmax>
            <ymax>1540.462402</ymax>
        </bndbox>
    </object>
    <object>
        <name>door</name>
        <pose>Unspecified</pose>
        <truncated>0</truncated>
        <occluded>0</occluded>
        <difficult>0</difficult>
        <polygon>
            <x1>1699.658978</x1>
            <y1>1737.140311</y1>
            <x2>1709.122305</x2>
            <y2>1735.940558</y2>
            <x3>1709.122305</x3>
            <y3>1739.833634</y3>
            <x4>1735.856203</x4>
            <y4>1746.648556</y4>
            <x5>1771.311045</x5>
            <y5>1769.305113</y5>
            <x6>1782.022552</x6>
            <y6>1784.387721</y6>
            <x7>1794.536986</x7>
            <y7>1807.272802</y7>
            <x8>1803.894258</x8>
            <y8>1837.299270</y8>
            <x9>1802.344230</x9>
            <y9>1839.453928</y9>
            <x10>1713.764230</x10>
            <y10>1840.727135</y10>
            <x11>1712.214202</x11>
            <y11>1847.452280</y11>
            <x12>1702.041126</x12>
            <y12>1847.150302</y12>
            <x13>1694.698890</x13>
            <y13>1738.454326</y13>
        </polygon>
        <bndbox>
            <xmin>1694.698853</xmin>
            <ymin>1735.940552</ymin>
            <xmax>1803.894287</xmax>
            <ymax>1847.452271</ymax>
        </bndbox>
    </object>
    <object>
        <name>window</name>
        <pose>Unspecified</pose>
        <truncated>0</truncated>
        <occluded>0</occluded>
        <difficult>0</difficult>
        <polygon>
            <x1>1227.363001</x1>
            <y1>1440.246294</y1>
            <x2>1280.649129</x2>
            <y2>1443.673845</y2>
            <x3>1280.556862</x3>
            <y3>1522.911796</y3>
            <x4>1225.864768</x4>
            <y4>1519.044815</y4>
        </polygon>
        <bndbox>
            <xmin>1225.864746</xmin>
            <ymin>1440.246338</ymin>
            <xmax>1280.649170</xmax>
            <ymax>1522.911743</ymax>
        </bndbox>
    </object>
    <object>
        <name>window</name>
        <pose>Unspecified</pose>
        <truncated>0</truncated>
        <occluded>0</occluded>
        <difficult>0</difficult>
        <polygon>
            <x1>1041.894062</x1>
            <y1>1556.572106</y1>
            <x2>1144.059491</x2>
            <y2>1556.822580</y2>
            <x3>1147.969835</x3>
            <y3>1557.090633</y3>
            <x4>1149.090214</x4>
            <y4>1568.252145</y4>
            <x5>1144.490068</x5>
            <y5>1571.938960</y5>
            <x6>1144.490068</x6>
            <y6>1583.988120</y6>
            <x7>1141.309069</x7>
            <y7>1598.199275</y7>
            <x8>1133.264305</x8>
            <y8>1618.773370</y8>
            <x9>1116.550879</x9>
            <y9>1641.092001</y9>
            <x10>1103.141474</x10>
            <y10>1653.729997</y10>
            <x11>1086.744391</x11>
            <y11>1659.701846</y11>
            <x12>1074.007213</x12>
            <y12>1667.356710</y12>
            <x13>1053.546008</x13>
            <y13>1670.248157</y13>
            <x14>1042.733248</x14>
            <y14>1668.841982</y14>
            <x15>1042.632194</x15>
            <y15>1569.078273</y15>
            <x16>1038.761393</x16>
            <y16>1569.640743</y16>
            <x17>1040.901098</x17>
            <y17>1551.575791</y17>
        </polygon>
        <bndbox>
            <xmin>1038.761353</xmin>
            <ymin>1551.575806</ymin>
            <xmax>1149.090210</xmax>
            <ymax>1670.248169</ymax>
        </bndbox>
    </object>
    <object>
        <name>toilet</name>
        <pose>Unspecified</pose>
        <truncated>0</truncated>
        <occluded>0</occluded>
        <difficult>0</difficult>
        <polygon>
            <x1>969.289077</x1>
            <y1>1643.021097</y1>
            <x2>960.242561</x2>
            <y2>1628.985714</y2>
            <x3>957.698641</x3>
            <y3>1608.288579</y3>
            <x4>958.309358</x4>
            <y4>1595.887875</y4>
            <x5>953.252272</x5>
            <y5>1581.685509</y5>
            <x6>952.606406</x6>
            <y6>1571.156775</y6>
            <x7>952.606406</x7>
            <y7>1568.884924</y7>
            <x8>1010.725543</x8>
            <y8>1567.184331</y8>
            <x9>1010.725543</x9>
            <y9>1580.235391</y9>
            <x10>1010.154370</x10>
            <y10>1589.898449</y10>
            <x11>1005.747544</x11>
            <y11>1592.864599</y11>
            <x12>1006.907466</x12>
            <y12>1610.204492</y12>
            <x13>1005.286211</x13>
            <y13>1630.818136</y13>
            <x14>996.353930</x14>
            <y14>1645.552212</y14>
            <x15>984.139597</x15>
            <y15>1648.803991</y15>
            <x16>970.128263</x16>
            <y16>1645.991641</y16>
        </polygon>
        <bndbox>
            <xmin>952.606384</xmin>
            <ymin>1567.184326</ymin>
            <xmax>1010.725525</xmax>
            <ymax>1648.803955</ymax>
        </bndbox>
    </object>
    <object>
        <name>ceramic sink</name>
        <pose>Unspecified</pose>
        <truncated>0</truncated>
        <occluded>0</occluded>
        <difficult>0</difficult>
        <polygon>
            <x1>850.814437</x1>
            <y1>1671.425828</y1>
            <x2>925.396562</x2>
            <y2>1673.838297</y2>
            <x3>927.900940</x3>
            <y3>1761.227668</y3>
            <x4>849.891772</x4>
            <y4>1760.555340</y4>
        </polygon>
        <bndbox>
            <xmin>849.891785</xmin>
            <ymin>1671.425781</ymin>
            <xmax>927.900940</xmax>
            <ymax>1761.227661</ymax>
        </bndbox>
    </object>
    <object>
        <name>ceramic sink</name>
        <pose>Unspecified</pose>
        <truncated>0</truncated>
        <occluded>0</occluded>
        <difficult>0</difficult>
        <polygon>
            <x1>847.132563</x1>
            <y1>1562.311057</y1>
            <x2>928.146984</x2>
            <y2>1565.527681</y2>
            <x3>924.465110</x3>
            <y3>1660.532368</y3>
            <x4>847.286340</x4>
            <y4>1656.335815</y4>
            <x5>846.284589</x5>
            <y5>1570.954637</y5>
        </polygon>
        <bndbox>
            <xmin>846.284607</xmin>
            <ymin>1562.311035</ymin>
            <xmax>928.146973</xmax>
            <ymax>1660.532349</ymax>
        </bndbox>
    </object>
    <object>
        <name>window</name>
        <pose>Unspecified</pose>
        <truncated>0</truncated>
        <occluded>0</occluded>
        <difficult>0</difficult>
        <polygon>
            <x1>231.358811</x1>
            <y1>1597.715902</y1>
            <x2>231.284119</x2>
            <y2>1770.824811</y2>
            <x3>282.808395</x3>
            <y3>1770.600702</y3>
            <x4>283.612432</x4>
            <y4>1600.361268</y4>
            <x5>240.646977</x5>
            <y5>1601.828963</y5>
        </polygon>
        <bndbox>
            <xmin>231.284119</xmin>
            <ymin>1597.715942</ymin>
            <xmax>283.612427</xmax>
            <ymax>1770.824829</ymax>
        </bndbox>
    </object>
    <object>
        <name>window</name>
        <pose>Unspecified</pose>
        <truncated>0</truncated>
        <occluded>0</occluded>
        <difficult>0</difficult>
        <polygon>
            <x1>742.014604</x1>
            <y1>1396.676846</y1>
            <x2>740.718479</x2>
            <y2>1450.599256</y2>
            <x3>826.983306</x3>
            <y3>1448.428473</y3>
            <x4>823.297038</x4>
            <y4>1394.734567</y4>
        </polygon>
        <bndbox>
            <xmin>740.718506</xmin>
            <ymin>1394.734619</ymin>
            <xmax>826.983276</xmax>
            <ymax>1450.599243</ymax>
        </bndbox>
    </object>
    <object>
        <name>bath tab</name>
        <pose>Unspecified</pose>
        <truncated>0</truncated>
        <occluded>0</occluded>
        <difficult>0</difficult>
        <polygon>
            <x1>663.284878</x1>
            <y1>1446.424674</y1>
            <x2>662.937780</x2>
            <y2>1534.174377</y2>
            <x3>865.344221</x3>
            <y3>1532.350744</y3>
            <x4>866.389909</x4>
            <y4>1446.697121</y4>
            <x5>666.610867</x5>
            <y5>1446.042370</y5>
        </polygon>
        <bndbox>
            <xmin>662.937805</xmin>
            <ymin>1446.042358</ymin>
            <xmax>866.389893</xmax>
            <ymax>1534.174316</ymax>
        </bndbox>
    </object>
    <object>
        <name>window</name>
        <pose>Unspecified</pose>
        <truncated>0</truncated>
        <occluded>0</occluded>
        <difficult>0</difficult>
        <polygon>
            <x1>2009.787710</x1>
            <y1>1955.754377</y1>
            <x2>1992.428419</x2>
            <y2>1916.636351</y2>
            <x3>1967.147385</x3>
            <y3>1902.034104</y3>
            <x4>1934.370792</x4>
            <y4>1892.854419</y4>
            <x5>1922.398110</x5>
            <y5>1893.113683</y5>
            <x6>1923.413042</x6>
            <y6>2025.430339</y6>
            <x7>2096.201922</x7>
            <y7>2024.995304</y7>
            <x8>2096.944448</x8>
            <y8>1979.505548</y8>
            <x9>2092.542015</x9>
            <y9>1975.902225</y9>
            <x10>2091.588594</x10>
            <y10>1890.644088</y10>
            <x11>2045.477289</x11>
            <y11>1902.306551</y11>
            <x12>2022.234907</x12>
            <y12>1922.634565</y12>
            <x13>2009.343952</x13>
            <y13>1950.661387</y13>
        </polygon>
        <bndbox>
            <xmin>1922.398071</xmin>
            <ymin>1890.644043</ymin>
            <xmax>2096.944336</xmax>
            <ymax>2025.430298</ymax>
        </bndbox>
    </object>
    <object>
        <name>window</name>
        <pose>Unspecified</pose>
        <truncated>0</truncated>
        <occluded>0</occluded>
        <difficult>0</difficult>
        <polygon>
            <x1>1601.455518</x1>
            <y1>2380.652070</y1>
            <x2>1584.096226</x2>
            <y2>2341.534044</y2>
            <x3>1558.815192</x3>
            <y3>2326.931798</y3>
            <x4>1526.038600</x4>
            <y4>2317.752113</y4>
            <x5>1514.065917</x5>
            <y5>2318.011376</y5>
            <x6>1515.080849</x6>
            <y6>2450.328032</y6>
            <x7>1687.869729</x7>
            <y7>2449.892997</y7>
            <x8>1688.612255</x8>
            <y8>2404.403242</y8>
            <x9>1684.209823</x9>
            <y9>2400.799919</y9>
            <x10>1683.256402</x10>
            <y10>2315.541782</y10>
            <x11>1637.145097</x11>
            <y11>2327.204244</y11>
            <x12>1613.902714</x12>
            <y12>2347.532259</y12>
            <x13>1601.011760</x13>
            <y13>2375.559081</y13>
        </polygon>
        <bndbox>
            <xmin>1514.065918</xmin>
            <ymin>2315.541748</ymin>
            <xmax>1688.612305</xmax>
            <ymax>2450.328125</ymax>
        </bndbox>
    </object>
    <object>
        <name>window</name>
        <pose>Unspecified</pose>
        <truncated>0</truncated>
        <occluded>0</occluded>
        <difficult>0</difficult>
        <polygon>
            <x1>1716.431870</x1>
            <y1>2222.397234</y1>
            <x2>1716.000379</x2>
            <y2>2215.437264</y2>
            <x3>1720.527327</x3>
            <y3>2227.237078</y3>
            <x4>1705.813501</x4>
            <y4>2252.458274</y4>
            <x5>1696.486253</x5>
            <y5>2285.202008</y5>
            <x6>1696.690444</x6>
            <y6>2297.179298</y6>
            <x7>1828.971187</x7>
            <y7>2296.771386</y7>
            <x8>1829.329316</x8>
            <y8>2123.931440</y8>
            <x9>1783.856885</x9>
            <y9>2122.979921</y9>
            <x10>1780.234465</x10>
            <y10>2127.367058</y10>
            <x11>1694.998130</x11>
            <y11>2127.929467</y11>
            <x12>1706.445375</x12>
            <y12>2174.107324</y12>
            <x13>1726.660479</x13>
            <y13>2197.449639</y13>
            <x14>1754.619549</x14>
            <y14>2210.472896</y14>
        </polygon>
        <bndbox>
            <xmin>1694.998169</xmin>
            <ymin>2122.979980</ymin>
            <xmax>1829.329346</xmax>
            <ymax>2297.179199</ymax>
        </bndbox>
    </object>
    <object>
        <name>window</name>
        <pose>Unspecified</pose>
        <truncated>0</truncated>
        <occluded>0</occluded>
        <difficult>0</difficult>
        <polygon>
            <x1>1235.763651</x1>
            <y1>2377.453022</y1>
            <x2>1218.404359</x2>
            <y2>2338.334996</y2>
            <x3>1193.123325</x3>
            <y3>2323.732750</y3>
            <x4>1160.346733</x4>
            <y4>2314.553065</y4>
            <x5>1148.374050</x5>
            <y5>2314.812328</y5>
            <x6>1149.388982</x6>
            <y6>2447.128985</y6>
            <x7>1322.177862</x7>
            <y7>2446.693949</y7>
            <x8>1322.920388</x8>
            <y8>2401.204194</y8>
            <x9>1318.517956</x9>
            <y9>2397.600871</y9>
            <x10>1317.564535</x10>
            <y10>2312.342734</y10>
            <x11>1271.453230</x11>
            <y11>2324.005196</y11>
            <x12>1248.210847</x12>
            <y12>2344.333211</y12>
            <x13>1235.319892</x13>
            <y13>2372.360033</y13>
        </polygon>
        <bndbox>
            <xmin>1148.374023</xmin>
            <ymin>2312.342773</ymin>
            <xmax>1322.920410</xmax>
            <ymax>2447.128906</ymax>
        </bndbox>
    </object>
    <object>
        <name>window</name>
        <pose>Unspecified</pose>
        <truncated>0</truncated>
        <occluded>0</occluded>
        <difficult>0</difficult>
        <polygon>
            <x1>757.506597</x1>
            <y1>2394.362274</y1>
            <x2>757.796577</x2>
            <y2>2457.503918</y2>
            <x3>939.561674</x3>
            <y3>2449.444779</y3>
            <x4>937.650438</x4>
            <y4>2393.399924</y4>
            <x5>762.260521</x5>
            <y5>2398.123792</y5>
        </polygon>
        <bndbox>
            <xmin>757.506592</xmin>
            <ymin>2393.399902</ymin>
            <xmax>939.561646</xmax>
            <ymax>2457.503906</ymax>
        </bndbox>
    </object>
    <object>
        <name>window</name>
        <pose>Unspecified</pose>
        <truncated>0</truncated>
        <occluded>0</occluded>
        <difficult>0</difficult>
        <polygon>
            <x1>395.887639</x1>
            <y1>2396.405622</y1>
            <x2>395.870064</x2>
            <y2>2452.810810</y2>
            <x3>568.013078</x3>
            <y3>2449.479933</y3>
            <x4>565.952459</x4>
            <y4>2393.856930</y4>
            <x5>392.341967</x5>
            <y5>2396.453960</y5>
        </polygon>
        <bndbox>
            <xmin>392.341980</xmin>
            <ymin>2393.856934</ymin>
            <xmax>568.013062</xmax>
            <ymax>2452.810791</ymax>
        </bndbox>
    </object>
    <object>
        <name>door</name>
        <pose>Unspecified</pose>
        <truncated>0</truncated>
        <occluded>0</occluded>
        <difficult>0</difficult>
        <polygon>
            <x1>1683.985747</x1>
            <y1>1533.075803</y1>
            <x2>1648.906884</x2>
            <y2>1543.569383</y2>
            <x3>1623.300721</x3>
            <y3>1558.729705</y3>
            <x4>1604.908923</x4>
            <y4>1583.469593</y4>
            <x5>1596.776286</x5>
            <y5>1606.148557</y5>
            <x6>1595.242904</x6>
            <y6>1620.175150</y6>
            <x7>1595.502129</x7>
            <y7>1628.489159</y7>
            <x8>1678.757309</x8>
            <y8>1627.474077</y8>
            <x9>1678.757309</x9>
            <y9>1632.483574</y9>
            <x10>1694.183397</x10>
            <y10>1631.921104</y10>
            <x11>1695.097275</x11>
            <y11>1528.149797</y11>
            <x12>1689.903987</x12>
            <y12>1527.618087</y12>
        </polygon>
        <bndbox>
            <xmin>1595.242920</xmin>
            <ymin>1527.618042</ymin>
            <xmax>1695.097290</xmax>
            <ymax>1632.483521</ymax>
        </bndbox>
    </object>
    <object>
        <name>door</name>
        <pose>Unspecified</pose>
        <truncated>0</truncated>
        <occluded>0</occluded>
        <difficult>0</difficult>
        <polygon>
            <x1>1027.381852</x1>
            <y1>1776.805448</y1>
            <x2>992.302990</x2>
            <y2>1787.299028</y2>
            <x3>966.696826</x3>
            <y3>1802.459350</y3>
            <x4>948.305028</x4>
            <y4>1827.199238</y4>
            <x5>940.172391</x5>
            <y5>1849.878201</y5>
            <x6>938.639009</x6>
            <y6>1863.904795</y6>
            <x7>938.898234</x7>
            <y7>1872.218804</y7>
            <x8>1022.153414</x8>
            <y8>1871.203721</y8>
            <x9>1022.153414</x9>
            <y9>1876.213219</y9>
            <x10>1037.579502</x10>
            <y10>1875.650749</y10>
            <x11>1038.493380</x11>
            <y11>1771.879442</y11>
            <x12>1033.300092</x12>
            <y12>1771.347732</y12>
        </polygon>
        <bndbox>
            <xmin>938.639038</xmin>
            <ymin>1771.347778</ymin>
            <xmax>1038.493408</xmax>
            <ymax>1876.213257</ymax>
        </bndbox>
    </object>
    <object>
        <name>door</name>
        <pose>Unspecified</pose>
        <truncated>0</truncated>
        <occluded>0</occluded>
        <difficult>0</difficult>
        <polygon>
            <x1>818.951723</x1>
            <y1>1766.540372</y1>
            <x2>719.334608</x2>
            <y2>1767.300585</y2>
            <x3>719.044628</x3>
            <y3>1757.940734</y3>
            <x4>723.715072</x4>
            <y4>1754.390143</y4>
            <x5>723.952329</x5>
            <y5>1670.415140</y5>
            <x6>727.555118</x6>
            <y6>1667.848871</y6>
            <x7>742.014604</x7>
            <y7>1666.403148</y7>
            <x8>762.739428</x8>
            <y8>1674.682002</y8>
            <x9>778.288538</x9>
            <y9>1680.311095</y9>
            <x10>787.704119</x10>
            <y10>1689.978547</y10>
            <x11>805.208401</x11>
            <y11>1703.258111</y11>
            <x12>814.637164</x12>
            <y12>1723.898120</y12>
            <x13>819.571227</x13>
            <y13>1751.902971</y13>
            <x14>820.775086</x14>
            <y14>1751.902971</y14>
            <x15>821.877891</x15>
            <y15>1762.664603</y15>
        </polygon>
        <bndbox>
            <xmin>719.044617</xmin>
            <ymin>1666.403198</ymin>
            <xmax>821.877869</xmax>
            <ymax>1767.300537</ymax>
        </bndbox>
    </object>
    <object>
        <name>door</name>
        <pose>Unspecified</pose>
        <truncated>0</truncated>
        <occluded>0</occluded>
        <difficult>0</difficult>
        <polygon>
            <x1>827.646747</x1>
            <y1>1944.821368</y1>
            <x2>769.009159</x2>
            <y2>1887.519744</y2>
            <x3>767.537288</x3>
            <y3>1887.519744</y3>
            <x4>770.085603</x4>
            <y4>1884.298724</y4>
            <x5>763.244697</x5>
            <y5>1873.866665</y5>
            <x6>694.277650</x6>
            <y6>1945.287163</y6>
            <x7>697.656363</x7>
            <y7>1952.985970</y7>
            <x8>702.335595</x8>
            <y8>1952.985970</y8>
            <x9>715.336391</x9>
            <y9>1960.342022</y9>
            <x10>720.687851</x10>
            <y10>1965.307577</y10>
            <x11>734.703579</x11>
            <y11>1969.965531</y11>
            <x12>750.551457</x12>
            <y12>1973.577643</y12>
            <x13>771.039024</x13>
            <y13>1976.130729</y13>
            <x14>793.204963</x14>
            <y14>1971.718855</y14>
            <x15>809.799760</x15>
            <y15>1965.039525</y15>
            <x16>825.129188</x16>
            <y16>1954.879912</y16>
            <x17>828.310187</x17>
            <y17>1946.965784</y17>
        </polygon>
        <bndbox>
            <xmin>694.277649</xmin>
            <ymin>1873.866699</ymin>
            <xmax>828.310181</xmax>
            <ymax>1976.130737</ymax>
        </bndbox>
    </object>
    <object>
        <name>door</name>
        <pose>Unspecified</pose>
        <truncated>0</truncated>
        <occluded>0</occluded>
        <difficult>0</difficult>
        <polygon>
            <x1>618.746498</x1>
            <y1>2004.535460</y1>
            <x2>676.856848</x2>
            <y2>1944.557710</y2>
            <x3>680.797947</x3>
            <y3>1947.734786</y3>
            <x4>691.391026</x4>
            <y4>1935.395602</y4>
            <x5>620.029442</x5>
            <y5>1866.677596</y5>
            <x6>611.154279</x6>
            <y6>1866.128309</y6>
            <x7>608.847615</x7>
            <y7>1869.503129</y7>
            <x8>610.794000</x8>
            <y8>1878.862980</y8>
            <x9>597.542767</x9>
            <y9>1897.732088</y9>
            <x10>592.564767</x10>
            <y10>1914.904998</y10>
            <x11>588.896073</x11>
            <y11>1933.220425</y11>
            <x12>588.333687</x12>
            <y12>1947.945712</y12>
            <x13>592.178126</x13>
            <y13>1973.261253</y13>
            <x14>602.876652</x14>
            <y14>1988.157918</y14>
            <x15>609.326523</x15>
            <y15>1999.815986</y15>
        </polygon>
        <bndbox>
            <xmin>588.333679</xmin>
            <ymin>1866.128296</ymin>
            <xmax>691.391052</xmax>
            <ymax>2004.535400</ymax>
        </bndbox>
    </object>
    <object>
        <name>door</name>
        <pose>Unspecified</pose>
        <truncated>0</truncated>
        <occluded>0</occluded>
        <difficult>0</difficult>
        <polygon>
            <x1>695.529839</x1>
            <y1>1796.122775</y1>
            <x2>622.059306</x2>
            <y2>1868.804436</y2>
            <x3>616.527707</x3>
            <y3>1862.872136</y3>
            <x4>616.527707</x4>
            <y4>1862.608478</y4>
            <x5>617.718385</x5>
            <y5>1855.212877</y5>
            <x6>555.473615</x6>
            <y6>1793.525746</y6>
            <x7>570.245050</x7>
            <y7>1780.514234</y7>
            <x8>592.200094</x8>
            <y8>1771.677304</y8>
            <x9>607.529522</x9>
            <y9>1765.072677</y9>
            <x10>626.804443</x10>
            <y10>1764.022440</y10>
            <x11>643.895722</x11>
            <y11>1764.874934</y11>
            <x12>661.496664</x12>
            <y12>1772.683598</y12>
            <x13>682.054530</x13>
            <y13>1787.518742</y13>
            <x14>687.362053</x14>
            <y14>1784.056037</y14>
            <x15>690.960448</x15>
            <y15>1793.279665</y15>
        </polygon>
        <bndbox>
            <xmin>555.473633</xmin>
            <ymin>1764.022461</ymin>
            <xmax>695.529846</xmax>
            <ymax>1868.804443</ymax>
        </bndbox>
    </object>
</annotation>