<annotation>
    <folder>train</folder>
    <filename>IIb_GY0502.png</filename>
    <size>
        <width>1060</width>
        <height>1500</height>
        <depth>3</depth>
    </size>
    <object>
        <name>window</name>
        <pose>Unspecified</pose>
        <truncated>0</truncated>
        <occluded>0</occluded>
        <difficult>0</difficult>
        <polygon>
            <x1>549.503396</x1>
            <y1>266.659010</y1>
            <x2>550.219357</x2>
            <y2>281.533192</y2>
            <x3>582.428129</x3>
            <y3>281.919671</y3>
            <x4>582.732570</x4>
            <y4>266.504628</y4>
        </polygon>
        <bndbox>
            <xmin>549.503418</xmin>
            <ymin>266.504639</ymin>
            <xmax>582.732544</xmax>
            <ymax>281.919678</ymax>
        </bndbox>
    </object>
    <object>
        <name>window</name>
        <pose>Unspecified</pose>
        <truncated>0</truncated>
        <occluded>0</occluded>
        <difficult>0</difficult>
        <polygon>
            <x1>599.149707</x1>
            <y1>1077.692370</y1>
            <x2>569.796185</x2>
            <y2>1106.946248</y2>
            <x3>584.380431</x3>
            <y3>1122.301940</y3>
            <x4>614.533543</x4>
            <y4>1092.593955</y4>
        </polygon>
        <bndbox>
            <xmin>569.796204</xmin>
            <ymin>1077.692383</ymin>
            <xmax>614.533569</xmax>
            <ymax>1122.301880</ymax>
        </bndbox>
    </object>
    <object>
        <name>window</name>
        <pose>Unspecified</pose>
        <truncated>0</truncated>
        <occluded>0</occluded>
        <difficult>0</difficult>
        <polygon>
            <x1>532.673429</x1>
            <y1>1076.932881</y1>
            <x2>518.004598</x2>
            <y2>1091.711520</y2>
            <x3>517.487839</x3>
            <y3>1092.448535</y3>
            <x4>546.995992</x4>
            <y4>1122.330363</y4>
            <x5>563.065757</x5>
            <y5>1107.422829</y5>
            <x6>532.703827</x6>
            <y6>1076.601059</y6>
        </polygon>
        <bndbox>
            <xmin>517.487854</xmin>
            <ymin>1076.601074</ymin>
            <xmax>563.065735</xmax>
            <ymax>1122.330322</ymax>
        </bndbox>
    </object>
    <object>
        <name>sliding door</name>
        <pose>Unspecified</pose>
        <truncated>0</truncated>
        <occluded>0</occluded>
        <difficult>0</difficult>
        <polygon>
            <x1>417.381598</x1>
            <y1>959.560527</y1>
            <x2>401.769327</x2>
            <y2>975.595599</y2>
            <x3>488.957182</x3>
            <y3>1063.864855</y3>
            <x4>506.388481</x4>
            <y4>1047.685436</y4>
            <x5>418.013031</x5>
            <y5>959.445467</y5>
        </polygon>
        <bndbox>
            <xmin>401.769318</xmin>
            <ymin>959.445496</ymin>
            <xmax>506.388489</xmax>
            <ymax>1063.864868</ymax>
        </bndbox>
    </object>
    <object>
        <name>sliding door</name>
        <pose>Unspecified</pose>
        <truncated>0</truncated>
        <occluded>0</occluded>
        <difficult>0</difficult>
        <polygon>
            <x1>726.930925</x1>
            <y1>983.786091</y1>
            <x2>727.122431</x2>
            <y2>1005.693957</y2>
            <x3>849.723051</x3>
            <y3>1005.020413</y3>
            <x4>849.463428</x4>
            <y4>984.149687</y4>
        </polygon>
        <bndbox>
            <xmin>726.930908</xmin>
            <ymin>983.786072</ymin>
            <xmax>849.723022</xmax>
            <ymax>1005.693970</ymax>
        </bndbox>
    </object>
    <object>
        <name>window</name>
        <pose>Unspecified</pose>
        <truncated>0</truncated>
        <occluded>0</occluded>
        <difficult>0</difficult>
        <polygon>
            <x1>887.756077</x1>
            <y1>854.949120</y1>
            <x2>868.184602</x2>
            <y2>854.832678</y2>
            <x3>867.872993</x3>
            <y3>856.004882</y3>
            <x4>838.993200</x4>
            <y4>855.894183</y4>
            <x5>839.022856</x5>
            <y5>864.004177</y5>
            <x6>843.081609</x6>
            <y6>873.017823</y6>
            <x7>845.865627</x7>
            <y7>876.359379</y7>
            <x8>848.122944</x8>
            <y8>878.846970</y8>
            <x9>850.845456</x9>
            <y9>880.793197</y9>
            <x10>853.551075</x10>
            <y10>882.402777</y10>
            <x11>855.943965</x11>
            <y11>884.026871</y11>
            <x12>859.503739</x12>
            <y12>884.842709</y12>
            <x13>857.749949</x13>
            <y13>885.934537</y13>
            <x14>852.240171</x14>
            <y14>887.876431</y14>
            <x15>848.614343</x15>
            <y15>891.591678</y15>
            <x16>845.091819</x16>
            <y16>895.445138</y16>
            <x17>842.389232</x17>
            <y17>898.424268</y17>
            <x18>840.874103</x18>
            <y18>901.647760</y18>
            <x19>839.883725</x19>
            <y19>904.681265</y19>
            <x20>839.103853</x20>
            <y20>908.547939</y20>
            <x21>839.099955</x21>
            <y21>914.431895</y21>
            <x22>868.047024</x22>
            <y22>914.594586</y22>
            <x23>868.047024</x23>
            <y23>915.830908</y23>
            <x24>887.832499</x24>
            <y24>916.337828</y24>
            <x25>887.463246</x25>
            <y25>854.924674</y25>
        </polygon>
        <bndbox>
            <xmin>838.993225</xmin>
            <ymin>854.832703</ymin>
            <xmax>887.832520</xmax>
            <ymax>916.337830</ymax>
        </bndbox>
    </object>
    <object>
        <name>window</name>
        <pose>Unspecified</pose>
        <truncated>0</truncated>
        <occluded>0</occluded>
        <difficult>0</difficult>
        <polygon>
            <x1>888.683575</x1>
            <y1>700.466275</y1>
            <x2>888.426460</x2>
            <y2>763.694835</y2>
            <x3>866.464024</x3>
            <y3>762.951540</y3>
            <x4>865.477296</x4>
            <y4>699.889952</y4>
        </polygon>
        <bndbox>
            <xmin>865.477295</xmin>
            <ymin>699.889954</ymin>
            <xmax>888.683594</xmax>
            <ymax>763.694824</ymax>
        </bndbox>
    </object>
    <object>
        <name>door</name>
        <pose>Unspecified</pose>
        <truncated>0</truncated>
        <occluded>0</occluded>
        <difficult>0</difficult>
        <polygon>
            <x1>741.366822</x1>
            <y1>454.177187</y1>
            <x2>705.228004</x2>
            <y2>453.810306</y2>
            <x3>705.224128</x3>
            <y3>448.963538</y3>
            <x4>706.245887</x4>
            <y4>443.449903</y4>
            <x5>708.065766</x5>
            <y5>437.710807</y5>
            <x6>710.284177</x6>
            <y6>433.633004</y6>
            <x7>712.431173</x7>
            <y7>430.494054</y7>
            <x8>715.787860</x8>
            <y8>427.137397</y8>
            <x9>718.203951</x9>
            <y9>424.717009</y9>
            <x10>723.271282</x10>
            <y10>420.672220</y10>
            <x11>727.367243</x11>
            <y11>418.475413</y11>
            <x12>737.118759</x12>
            <y12>415.644049</y12>
            <x13>742.109978</x13>
            <y13>415.444435</y13>
            <x14>742.182684</x14>
            <y14>413.411525</y14>
            <x15>745.417685</x15>
            <y15>413.460518</y15>
            <x16>745.513530</x16>
            <y16>456.972284</y16>
            <x17>742.084607</x17>
            <y17>457.035845</y17>
            <x18>741.988762</x18>
            <y18>454.100151</y18>
        </polygon>
        <bndbox>
            <xmin>705.224121</xmin>
            <ymin>413.411530</ymin>
            <xmax>745.513550</xmax>
            <ymax>457.035858</ymax>
        </bndbox>
    </object>
    <object>
        <name>door</name>
        <pose>Unspecified</pose>
        <truncated>0</truncated>
        <occluded>0</occluded>
        <difficult>0</difficult>
        <polygon>
            <x1>703.029672</x1>
            <y1>467.374394</y1>
            <x2>702.995505</x2>
            <y2>504.096007</y2>
            <x3>693.610387</x3>
            <y3>503.605029</y3>
            <x4>681.926907</x4>
            <y4>498.439346</y4>
            <x5>672.967627</x5>
            <y5>491.478136</y5>
            <x6>667.318389</x6>
            <y6>482.067874</y6>
            <x7>664.199183</x7>
            <y7>474.178892</y7>
            <x8>664.199183</x8>
            <y8>469.519191</y8>
            <x9>662.465828</x9>
            <y9>468.904844</y9>
            <x10>662.104990</x10>
            <y10>462.869739</y10>
            <x11>706.531383</x11>
            <y11>462.585489</y11>
            <x12>705.721373</x12>
            <y12>467.683652</y12>
        </polygon>
        <bndbox>
            <xmin>662.104980</xmin>
            <ymin>462.585480</ymin>
            <xmax>706.531372</xmax>
            <ymax>504.096008</ymax>
        </bndbox>
    </object>
    <object>
        <name>window</name>
        <pose>Unspecified</pose>
        <truncated>0</truncated>
        <occluded>0</occluded>
        <difficult>0</difficult>
        <polygon>
            <x1>755.121161</x1>
            <y1>533.232059</y1>
            <x2>741.150152</x2>
            <y2>533.389605</y2>
            <x3>740.847648</x3>
            <y3>535.333509</y3>
            <x4>740.901816</x4>
            <y4>563.330060</y4>
            <x5>742.549336</x5>
            <y5>565.415672</y5>
            <x6>755.171995</x6>
            <y6>565.924155</y6>
        </polygon>
        <bndbox>
            <xmin>740.847656</xmin>
            <ymin>533.232056</ymin>
            <xmax>755.171997</xmax>
            <ymax>565.924133</ymax>
        </bndbox>
    </object>
    <object>
        <name>door</name>
        <pose>Unspecified</pose>
        <truncated>0</truncated>
        <occluded>0</occluded>
        <difficult>0</difficult>
        <polygon>
            <x1>702.132161</x1>
            <y1>640.539390</y1>
            <x2>702.217162</x2>
            <y2>677.922863</y2>
            <x3>710.346431</x3>
            <y3>677.977879</y3>
            <x4>714.943989</x4>
            <y4>676.678331</y4>
            <x5>720.346557</x5>
            <y5>675.048686</y5>
            <x6>725.842459</x6>
            <y6>671.100027</y6>
            <x7>731.815035</x7>
            <y7>666.052712</y7>
            <x8>736.114255</x8>
            <y8>660.145145</y8>
            <x9>740.104306</x9>
            <y9>650.678199</y9>
            <x10>740.740980</x10>
            <y10>645.876790</y10>
            <x11>740.718480</x11>
            <y11>640.621914</y11>
            <x12>742.551837</x12>
            <y12>640.621914</y12>
            <x13>742.437668</x13>
            <y13>636.829968</y13>
            <x14>699.965467</x14>
            <y14>636.847473</y14>
        </polygon>
        <bndbox>
            <xmin>699.965454</xmin>
            <ymin>636.829956</ymin>
            <xmax>742.551819</xmax>
            <ymax>677.977905</ymax>
        </bndbox>
    </object>
    <object>
        <name>door</name>
        <pose>Unspecified</pose>
        <truncated>0</truncated>
        <occluded>0</occluded>
        <difficult>0</difficult>
        <polygon>
            <x1>550.415937</x1>
            <y1>626.201505</y1>
            <x2>508.123527</x2>
            <y2>626.146531</y2>
            <x3>507.251870</x3>
            <y3>621.941338</y3>
            <x4>510.426844</x4>
            <y4>621.575306</y4>
            <x5>510.426844</x5>
            <y5>618.252486</y5>
            <x6>512.094332</x6>
            <y6>610.320169</y6>
            <x7>516.068615</x7>
            <y7>601.943880</y7>
            <x8>521.623429</x8>
            <y8>594.870276</y8>
            <x9>526.968154</x9>
            <y9>590.704748</y9>
            <x10>534.031150</x10>
            <y10>587.384713</y10>
            <x11>539.703530</x11>
            <y11>585.548985</y11>
            <x12>542.947374</x12>
            <y12>584.122435</y12>
            <x13>549.232626</x13>
            <y13>585.277593</y13>
            <x14>549.192974</x14>
            <y14>621.919070</y14>
            <x15>551.486552</x15>
            <y15>621.727703</y15>
        </polygon>
        <bndbox>
            <xmin>507.251862</xmin>
            <ymin>584.122437</ymin>
            <xmax>551.486572</xmax>
            <ymax>626.201477</ymax>
        </bndbox>
    </object>
    <object>
        <name>door</name>
        <pose>Unspecified</pose>
        <truncated>0</truncated>
        <occluded>0</occluded>
        <difficult>0</difficult>
        <polygon>
            <x1>503.581589</x1>
            <y1>633.774750</y1>
            <x2>503.861938</x2>
            <y2>670.020968</y2>
            <x3>496.241026</x3>
            <y3>670.078726</y3>
            <x4>489.109856</x4>
            <y4>668.437844</y4>
            <x5>483.024257</x5>
            <y5>665.323093</y5>
            <x6>476.400220</x6>
            <y6>660.591816</y6>
            <x7>469.590443</x7>
            <y7>651.761119</y7>
            <x8>466.048162</x8>
            <y8>643.805141</y8>
            <x9>464.900329</x9>
            <y9>639.986856</y9>
            <x10>464.949025</x10>
            <y10>633.813023</y10>
            <x11>462.430055</x11>
            <y11>633.633487</y11>
            <x12>462.471098</x12>
            <y12>628.961359</y12>
            <x13>505.802819</x13>
            <y13>629.281463</y13>
            <x14>505.756210</x14>
            <y14>634.375293</y14>
        </polygon>
        <bndbox>
            <xmin>462.430054</xmin>
            <ymin>628.961365</ymin>
            <xmax>505.802826</xmax>
            <ymax>670.078735</ymax>
        </bndbox>
    </object>
    <object>
        <name>ceramic sink</name>
        <pose>Unspecified</pose>
        <truncated>0</truncated>
        <occluded>0</occluded>
        <difficult>0</difficult>
        <polygon>
            <x1>591.910521</x1>
            <y1>728.529175</y1>
            <x2>591.832029</x2>
            <y2>711.355383</y2>
            <x3>589.701719</x3>
            <y3>706.720588</y3>
            <x4>583.782391</x4>
            <y4>703.961905</y4>
            <x5>576.956188</x5>
            <y5>702.362894</y5>
            <x6>569.049263</x6>
            <y6>703.411596</y6>
            <x7>561.062548</x7>
            <y7>708.260545</y7>
            <x8>559.634773</x8>
            <y8>711.962800</y8>
            <x9>560.193298</x9>
            <y9>729.141135</y9>
            <x10>592.130428</x10>
            <y10>729.024324</y10>
        </polygon>
        <bndbox>
            <xmin>559.634766</xmin>
            <ymin>702.362915</ymin>
            <xmax>592.130432</xmax>
            <ymax>729.141113</ymax>
        </bndbox>
    </object>
    <object>
        <name>toilet</name>
        <pose>Unspecified</pose>
        <truncated>0</truncated>
        <occluded>0</occluded>
        <difficult>0</difficult>
        <polygon>
            <x1>565.151231</x1>
            <y1>633.220738</y1>
            <x2>564.265278</x2>
            <y2>636.526207</y2>
            <x3>564.166574</x3>
            <y3>639.656341</y3>
            <x4>564.321437</x4>
            <y4>640.816608</y4>
            <x5>565.635561</x5>
            <y5>642.173317</y5>
            <x6>566.642342</x6>
            <y6>642.962490</y6>
            <x7>567.021161</x7>
            <y7>643.481001</y7>
            <x8>567.159347</x8>
            <y8>645.437931</y8>
            <x9>566.844856</x9>
            <y9>647.448653</y9>
            <x10>566.268969</x10>
            <y10>649.348726</y10>
            <x11>566.268969</x11>
            <y11>651.524909</y11>
            <x12>566.318661</x12>
            <y12>657.878802</y12>
            <x13>567.696773</x13>
            <y13>661.860752</y13>
            <x14>569.788958</x14>
            <y14>664.715119</y14>
            <x15>571.400215</x15>
            <y15>665.689839</y15>
            <x16>573.280697</x16>
            <y16>666.208350</y16>
            <x17>581.011603</x17>
            <y17>665.826361</y17>
            <x18>584.411785</x18>
            <y18>661.879137</y18>
            <x19>586.201051</x19>
            <y19>658.001365</y19>
            <x20>585.999558</x20>
            <y20>646.548833</y20>
            <x21>585.021368</x21>
            <y21>645.332050</y21>
            <x22>584.587751</x22>
            <y22>643.317243</y22>
            <x23>585.783771</x23>
            <y23>643.031602</y23>
            <x24>587.030505</x24>
            <y24>642.277156</y24>
            <x25>587.753767</x25>
            <y25>641.461428</y25>
            <x26>587.480118</x26>
            <y26>635.196734</y26>
            <x27>586.538686</x27>
            <y27>632.439056</y27>
        </polygon>
        <bndbox>
            <xmin>564.166565</xmin>
            <ymin>632.439026</ymin>
            <xmax>587.753784</xmax>
            <ymax>666.208374</ymax>
        </bndbox>
    </object>
    <object>
        <name>door</name>
        <pose>Unspecified</pose>
        <truncated>0</truncated>
        <occluded>0</occluded>
        <difficult>0</difficult>
        <polygon>
            <x1>550.187364</x1>
            <y1>668.106041</y1>
            <x2>550.206424</x2>
            <y2>671.302564</y2>
            <x3>531.890365</x3>
            <y3>701.926744</y3>
            <x4>532.168438</x4>
            <y4>703.600756</y4>
            <x5>535.444390</x5>
            <y5>706.018320</y5>
            <x6>540.148486</x6>
            <y6>707.759402</y6>
            <x7>543.012264</x7>
            <y7>708.353154</y7>
            <x8>546.120419</x8>
            <y8>708.345323</y8>
            <x9>549.975661</x9>
            <y9>708.936011</y9>
            <x10>550.241141</x10>
            <y10>711.163261</y10>
            <x11>554.135864</x11>
            <y11>711.271866</y11>
            <x12>553.783253</x12>
            <y12>668.264352</y12>
        </polygon>
        <bndbox>
            <xmin>531.890381</xmin>
            <ymin>668.106018</ymin>
            <xmax>554.135864</xmax>
            <ymax>711.271851</ymax>
        </bndbox>
    </object>
    <object>
        <name>door</name>
        <pose>Unspecified</pose>
        <truncated>0</truncated>
        <occluded>0</occluded>
        <difficult>0</difficult>
        <polygon>
            <x1>458.923560</x1>
            <y1>775.920074</y1>
            <x2>463.640179</x2>
            <y2>775.521027</y2>
            <x3>469.092091</x3>
            <y3>774.319440</y3>
            <x4>474.163577</x4>
            <y4>772.475746</y4>
            <x5>479.142827</x5>
            <y5>770.206699</y5>
            <x6>484.036879</x6>
            <y6>767.166235</y6>
            <x7>488.049690</x7>
            <y7>763.827875</y7>
            <x8>491.385366</x8>
            <y8>759.919289</y8>
            <x9>495.385212</x9>
            <y9>754.149595</y9>
            <x10>497.339574</x10>
            <y10>749.249875</y10>
            <x11>499.230222</x11>
            <y11>744.052259</y11>
            <x12>499.836237</x12>
            <y12>740.361167</y12>
            <x13>499.865871</x13>
            <y13>732.335023</y13>
            <x14>458.751313</x14>
            <y14>732.253509</y14>
            <x15>458.799838</x15>
            <y15>731.076376</y15>
            <x16>453.397563</x16>
            <y16>731.028209</y16>
            <x17>453.196793</x17>
            <y17>776.863782</y17>
            <x18>458.972827</x18>
            <y18>777.058674</y18>
        </polygon>
        <bndbox>
            <xmin>453.196808</xmin>
            <ymin>731.028198</ymin>
            <xmax>499.865875</xmax>
            <ymax>777.058655</ymax>
        </bndbox>
    </object>
    <object>
        <name>square bath tab</name>
        <pose>Unspecified</pose>
        <truncated>0</truncated>
        <occluded>0</occluded>
        <difficult>0</difficult>
        <polygon>
            <x1>462.395181</x1>
            <y1>685.293046</y1>
            <x2>462.504827</x2>
            <y2>725.975095</y2>
            <x3>503.714584</x3>
            <y3>725.795394</y3>
            <x4>503.714584</x4>
            <y4>685.360110</y4>
        </polygon>
        <bndbox>
            <xmin>462.395172</xmin>
            <ymin>685.293030</ymin>
            <xmax>503.714569</xmax>
            <ymax>725.975098</ymax>
        </bndbox>
    </object>
    <object>
        <name>ceramic sink</name>
        <pose>Unspecified</pose>
        <truncated>0</truncated>
        <occluded>0</occluded>
        <difficult>0</difficult>
        <polygon>
            <x1>412.191511</x1>
            <y1>692.409941</y1>
            <x2>412.462662</x2>
            <y2>709.016893</y2>
            <x3>444.961509</x3>
            <y3>708.915001</y3>
            <x4>444.630720</x4>
            <y4>692.601128</y4>
            <x5>443.342012</x5>
            <y5>688.511359</y5>
            <x6>440.141542</x6>
            <y6>685.468301</y6>
            <x7>436.938479</x7>
            <y7>683.674257</y7>
            <x8>431.974417</x8>
            <y8>682.181813</y8>
            <x9>427.718236</x9>
            <y9>682.129571</y9>
            <x10>423.546882</x10>
            <y10>681.987292</y10>
            <x11>418.636531</x11>
            <y11>684.590175</y11>
            <x12>413.789523</x12>
            <y12>688.363523</y12>
            <x13>412.232257</x13>
            <y13>691.816743</y13>
        </polygon>
        <bndbox>
            <xmin>412.191498</xmin>
            <ymin>681.987305</ymin>
            <xmax>444.961517</xmax>
            <ymax>709.016907</ymax>
        </bndbox>
    </object>
    <object>
        <name>window</name>
        <pose>Unspecified</pose>
        <truncated>0</truncated>
        <occluded>0</occluded>
        <difficult>0</difficult>
        <polygon>
            <x1>377.163773</x1>
            <y1>669.182588</y1>
            <x2>377.231931</x2>
            <y2>701.711035</y2>
            <x3>398.124630</x3>
            <y3>701.955205</y3>
            <x4>398.976607</x4>
            <y4>700.771032</y4>
            <x5>398.729904</x5>
            <y5>671.308615</y5>
            <x6>396.919638</x6>
            <y6>670.039594</y6>
        </polygon>
        <bndbox>
            <xmin>377.163788</xmin>
            <ymin>669.182617</ymin>
            <xmax>398.976593</xmax>
            <ymax>701.955200</ymax>
        </bndbox>
    </object>
    <object>
        <name>window</name>
        <pose>Unspecified</pose>
        <truncated>0</truncated>
        <occluded>0</occluded>
        <difficult>0</difficult>
        <polygon>
            <x1>376.719985</x1>
            <y1>511.722077</y1>
            <x2>376.485465</x2>
            <y2>575.691850</y2>
            <x3>400.049308</x3>
            <y3>576.101943</y3>
            <x4>399.289835</x4>
            <y4>512.546923</y4>
        </polygon>
        <bndbox>
            <xmin>376.485474</xmin>
            <ymin>511.722076</ymin>
            <xmax>400.049316</xmax>
            <ymax>576.101929</ymax>
        </bndbox>
    </object>
</annotation>