<annotation>
    <folder>train</folder>
    <filename>Z-IId_LA0401.png</filename>
    <size>
        <width>2479</width>
        <height>3508</height>
        <depth>3</depth>
    </size>
    <object>
        <name>window</name>
        <pose>Unspecified</pose>
        <truncated>0</truncated>
        <occluded>0</occluded>
        <difficult>0</difficult>
        <polygon>
            <x1>1386.744236</x1>
            <y1>2136.644415</y1>
            <x2>1350.460377</x2>
            <y2>2175.923898</y2>
            <x3>1454.560187</x3>
            <y3>2278.935775</y3>
            <x4>1491.257093</x4>
            <y4>2243.454060</y4>
        </polygon>
        <bndbox>
            <xmin>1350.460327</xmin>
            <ymin>2136.644531</ymin>
            <xmax>1491.257080</xmax>
            <ymax>2278.935791</ymax>
        </bndbox>
    </object>
    <object>
        <name>sliding door</name>
        <pose>Unspecified</pose>
        <truncated>0</truncated>
        <occluded>0</occluded>
        <difficult>0</difficult>
        <bndbox>
            <xmin>731.705139</xmin>
            <ymin>1759.498657</ymin>
            <xmax>786.682983</xmax>
            <ymax>2053.414795</ymax>
        </bndbox>
    </object>
    <object>
        <name>sliding door</name>
        <pose>Unspecified</pose>
        <truncated>0</truncated>
        <occluded>0</occluded>
        <difficult>0</difficult>
        <bndbox>
            <xmin>788.682129</xmin>
            <ymin>2055.414062</ymin>
            <xmax>1086.561890</xmax>
            <ymax>2110.398438</ymax>
        </bndbox>
    </object>
    <object>
        <name>window</name>
        <pose>Unspecified</pose>
        <truncated>0</truncated>
        <occluded>0</occluded>
        <difficult>0</difficult>
        <bndbox>
            <xmin>493.801117</xmin>
            <ymin>1013.711243</ymin>
            <xmax>549.778564</xmax>
            <ymax>1238.647217</ymax>
        </bndbox>
    </object>
    <object>
        <name>window</name>
        <pose>Unspecified</pose>
        <truncated>0</truncated>
        <occluded>0</occluded>
        <difficult>0</difficult>
        <bndbox>
            <xmin>1787.279175</xmin>
            <ymin>1667.524658</ymin>
            <xmax>1875.243774</xmax>
            <ymax>1752.500488</ymax>
        </bndbox>
    </object>
    <object>
        <name>window</name>
        <pose>Unspecified</pose>
        <truncated>0</truncated>
        <occluded>0</occluded>
        <difficult>0</difficult>
        <bndbox>
            <xmin>1869.245972</xmin>
            <ymin>1808.484619</ymin>
            <xmax>1921.225098</xmax>
            <ymax>1884.463013</ymax>
        </bndbox>
    </object>
    <object>
        <name>door</name>
        <pose>Unspecified</pose>
        <truncated>0</truncated>
        <occluded>0</occluded>
        <difficult>0</difficult>
        <polygon>
            <x1>1696.428917</x1>
            <y1>1868.823330</y1>
            <x2>1696.245181</x2>
            <y2>1874.406997</y2>
            <x3>1688.576298</x3>
            <y3>1874.352606</y3>
            <x4>1688.750724</x4>
            <y4>1774.019561</y4>
            <x5>1696.792959</x5>
            <y5>1773.919599</y5>
            <x6>1696.867923</x6>
            <y6>1779.854114</y6>
            <x7>1783.874869</x7>
            <y7>1779.982007</y7>
            <x8>1782.928263</x8>
            <y8>1791.619262</y8>
            <x9>1779.586233</x9>
            <y9>1806.424434</y9>
            <x10>1774.504348</x10>
            <y10>1819.497910</y10>
            <x11>1767.725725</x11>
            <y11>1831.932412</y11>
            <x12>1758.721695</x12>
            <y12>1842.462244</y12>
            <x13>1742.756776</x13>
            <y13>1855.714083</y13>
            <x14>1729.759066</x14>
            <y14>1862.096958</y14>
            <x15>1716.715300</x15>
            <y15>1866.733436</y15>
            <x16>1708.337931</x16>
            <y16>1868.410251</y16>
            <x17>1698.810132</x17>
            <y17>1869.359401</y17>
        </polygon>
        <bndbox>
            <xmin>1688.576294</xmin>
            <ymin>1773.919556</ymin>
            <xmax>1783.874878</xmax>
            <ymax>1874.406982</ymax>
        </bndbox>
    </object>
    <object>
        <name>door</name>
        <pose>Unspecified</pose>
        <truncated>0</truncated>
        <occluded>0</occluded>
        <difficult>0</difficult>
        <polygon>
            <x1>1589.260533</x1>
            <y1>1873.094063</y1>
            <x2>1589.364126</x2>
            <y2>1881.802826</y2>
            <x3>1594.977923</x3>
            <y3>1881.779659</y3>
            <x4>1595.102859</x4>
            <y4>1885.841839</y4>
            <x5>1595.956329</x5>
            <y5>1894.189028</y5>
            <x6>1597.519072</x6>
            <y6>1903.128167</y6>
            <x7>1599.855898</x7>
            <y7>1910.010836</y7>
            <x8>1603.311423</x8>
            <y8>1918.623284</y8>
            <x9>1609.848707</x9>
            <y9>1929.833392</y9>
            <x10>1618.242593</x10>
            <y10>1939.708096</y10>
            <x11>1630.337713</x11>
            <y11>1951.416963</y11>
            <x12>1646.348799</x12>
            <y12>1960.839504</y12>
            <x13>1666.880492</x13>
            <y13>1967.122933</y13>
            <x14>1674.362604</x14>
            <y14>1967.967648</y14>
            <x15>1683.521725</x15>
            <y15>1967.847904</y15>
            <x16>1683.507930</x16>
            <y16>1881.802566</y16>
            <x17>1689.935113</x17>
            <y17>1881.903047</y17>
            <x18>1690.085557</x18>
            <y18>1872.881127</y18>
        </polygon>
        <bndbox>
            <xmin>1589.260498</xmin>
            <ymin>1872.881104</ymin>
            <xmax>1690.085571</xmax>
            <ymax>1967.967651</ymax>
        </bndbox>
    </object>
    <object>
        <name>ceramic sink</name>
        <pose>Unspecified</pose>
        <truncated>0</truncated>
        <occluded>0</occluded>
        <difficult>0</difficult>
        <polygon>
            <x1>1788.859925</x1>
            <y1>1956.595127</y1>
            <x2>1788.697061</x2>
            <y2>1919.381725</y2>
            <x3>1790.954502</x3>
            <y3>1913.142241</y3>
            <x4>1796.310642</x4>
            <y4>1906.981749</y4>
            <x5>1799.984570</x5>
            <y5>1903.654268</y5>
            <x6>1804.770687</x6>
            <y6>1901.054866</y6>
            <x7>1811.800163</x7>
            <y7>1898.415661</y7>
            <x8>1819.189347</x8>
            <y8>1897.064523</y8>
            <x9>1831.590882</x9>
            <y9>1897.230774</y9>
            <x10>1840.924943</x10>
            <y10>1899.288864</y10>
            <x11>1849.319782</x11>
            <y11>1902.634409</y11>
            <x12>1853.161472</x12>
            <y12>1905.686946</y12>
            <x13>1858.535980</x13>
            <y13>1911.152121</y13>
            <x14>1860.556472</x14>
            <y14>1915.010198</y14>
            <x15>1861.481613</x15>
            <y15>1918.809183</y15>
            <x16>1861.491715</x16>
            <y16>1956.619009</y16>
        </polygon>
        <bndbox>
            <xmin>1788.697021</xmin>
            <ymin>1897.064575</ymin>
            <xmax>1861.491699</xmax>
            <ymax>1956.619019</ymax>
        </bndbox>
    </object>
    <object>
        <name>toilet</name>
        <pose>Unspecified</pose>
        <truncated>0</truncated>
        <occluded>0</occluded>
        <difficult>0</difficult>
        <polygon>
            <x1>1689.699369</x1>
            <y1>1735.381048</y1>
            <x2>1684.997897</x2>
            <y2>1737.983854</y2>
            <x3>1681.361478</x3>
            <y3>1739.071137</y3>
            <x4>1671.038161</x4>
            <y4>1738.968809</y4>
            <x5>1667.975962</x5>
            <y5>1736.707244</y5>
            <x6>1666.510667</x6>
            <y6>1732.379751</y6>
            <x7>1661.529297</x7>
            <y7>1732.422124</y7>
            <x8>1652.035757</x8>
            <y8>1734.235614</y8>
            <x9>1630.642728</x9>
            <y9>1734.174308</y9>
            <x10>1623.783654</x10>
            <y10>1731.444382</y10>
            <x11>1620.641226</x11>
            <y11>1729.428041</y11>
            <x12>1615.735577</x12>
            <y12>1724.424828</y12>
            <x13>1614.079627</x13>
            <y13>1721.168390</y13>
            <x14>1613.001052</x14>
            <y14>1718.147259</y14>
            <x15>1612.823017</x15>
            <y15>1704.962381</y15>
            <x16>1616.123648</x16>
            <y16>1699.113053</y16>
            <x17>1621.827524</x17>
            <y17>1694.436657</y17>
            <x18>1628.198468</x18>
            <y18>1691.512444</y18>
            <x19>1634.934044</x19>
            <y19>1690.171823</y19>
            <x20>1648.722957</x20>
            <y20>1690.239440</y20>
            <x21>1656.687650</x21>
            <y21>1691.769389</y21>
            <x22>1663.828425</x22>
            <y22>1691.999287</y22>
            <x23>1666.418720</x23>
            <y23>1692.501005</y23>
            <x24>1667.727614</x24>
            <y24>1687.965703</y24>
            <x25>1671.477614</x25>
            <y25>1685.667624</y25>
            <x26>1674.694862</x26>
            <y26>1684.923836</y26>
            <x27>1681.237079</x27>
            <y27>1685.611276</y27>
            <x28>1684.381761</x28>
            <y28>1686.807648</y28>
            <x29>1689.204928</x29>
            <y29>1688.293420</y29>
        </polygon>
        <bndbox>
            <xmin>1612.822998</xmin>
            <ymin>1684.923828</ymin>
            <xmax>1689.699341</xmax>
            <ymax>1739.071167</ymax>
        </bndbox>
    </object>
    <object>
        <name>door</name>
        <pose>Unspecified</pose>
        <truncated>0</truncated>
        <occluded>0</occluded>
        <difficult>0</difficult>
        <polygon>
            <x1>1630.200588</x1>
            <y1>1776.503547</y1>
            <x2>1555.143771</x2>
            <y2>1820.086657</y2>
            <x3>1553.205313</x3>
            <y3>1818.743664</y3>
            <x4>1543.480944</x4>
            <y4>1799.657575</y4>
            <x5>1541.130049</x5>
            <y5>1776.604386</y5>
            <x6>1534.004039</x6>
            <y6>1776.604386</y6>
            <x7>1534.004039</x7>
            <y7>1766.857371</y7>
            <x8>1637.885680</x8>
            <y8>1766.839037</y8>
            <x9>1637.113505</x9>
            <y9>1777.014617</y9>
        </polygon>
        <bndbox>
            <xmin>1534.004028</xmin>
            <ymin>1766.838989</ymin>
            <xmax>1637.885620</xmax>
            <ymax>1820.086670</ymax>
        </bndbox>
    </object>
    <object>
        <name>door</name>
        <pose>Unspecified</pose>
        <truncated>0</truncated>
        <occluded>0</occluded>
        <difficult>0</difficult>
        <polygon>
            <x1>1021.191331</x1>
            <y1>1121.910860</y1>
            <x2>1021.243537</x2>
            <y2>1223.679282</y2>
            <x3>1030.623968</x3>
            <y3>1223.898387</y3>
            <x4>1030.565236</x4>
            <y4>1217.727072</y4>
            <x5>1115.940956</x5>
            <y5>1216.884216</y5>
            <x6>1115.728400</x6>
            <y6>1210.337158</y6>
            <x7>1114.561207</x7>
            <y7>1198.699396</y7>
            <x8>1110.236438</x8>
            <y8>1182.108917</y8>
            <x9>1103.892388</x9>
            <y9>1169.890292</y9>
            <x10>1096.837953</x10>
            <y10>1159.898151</y10>
            <x11>1084.784724</x11>
            <y11>1147.611463</y11>
            <x12>1074.376939</x12>
            <y12>1139.649078</y12>
            <x13>1058.821197</x13>
            <y13>1131.812561</y13>
            <x14>1046.640248</x14>
            <y14>1128.707791</y14>
            <x15>1035.957445</x15>
            <y15>1127.696176</y15>
            <x16>1030.063678</x16>
            <y16>1127.814586</y16>
            <x17>1029.972317</x17>
            <y17>1121.518335</y17>
        </polygon>
        <bndbox>
            <xmin>1021.191345</xmin>
            <ymin>1121.518311</ymin>
            <xmax>1115.940918</xmax>
            <ymax>1223.898438</ymax>
        </bndbox>
    </object>
    <object>
        <name>door</name>
        <pose>Unspecified</pose>
        <truncated>0</truncated>
        <occluded>0</occluded>
        <difficult>0</difficult>
        <polygon>
            <x1>758.133436</x1>
            <y1>1512.547575</y1>
            <x2>819.231710</x2>
            <y2>1451.578222</y2>
            <x3>816.329146</x3>
            <y3>1448.147506</y3>
            <x4>806.621980</x4>
            <y4>1439.583497</y4>
            <x5>785.034877</x5>
            <y5>1428.702093</y5>
            <x6>765.331693</x6>
            <y6>1424.941598</y6>
            <x7>749.531826</x7>
            <y7>1424.579865</y7>
            <x8>730.332213</x8>
            <y8>1428.138402</y8>
            <x9>710.915324</x9>
            <y9>1436.688351</y9>
            <x10>699.366415</x10>
            <y10>1445.637101</y10>
            <x11>694.954415</x11>
            <y11>1450.385652</y11>
            <x12>692.228229</x12>
            <y12>1448.855634</y12>
            <x13>659.889752</x13>
            <y13>1479.625991</y13>
            <x14>729.266278</x14>
            <y14>1548.285056</y14>
            <x15>760.200123</x15>
            <y15>1516.966348</y15>
        </polygon>
        <bndbox>
            <xmin>659.889771</xmin>
            <ymin>1424.579834</ymin>
            <xmax>819.231689</xmax>
            <ymax>1548.285034</ymax>
        </bndbox>
    </object>
</annotation>